README.md
setup.py
BrowserAutomator/__init__.py
BrowserAutomator/cipher_util.py
BrowserAutomator/file_reader.py
BrowserAutomator/logging_util.py
BrowserAutomator/loop_actions.py
BrowserAutomator/network.py
BrowserAutomator/runner.py
BrowserAutomator/selenium_setup.py
BrowserAutomator/setup.py
BrowserAutomator/setup_actions.py
BrowserAutomator.egg-info/PKG-INFO
BrowserAutomator.egg-info/SOURCES.txt
BrowserAutomator.egg-info/dependency_links.txt
BrowserAutomator.egg-info/requires.txt
BrowserAutomator.egg-info/top_level.txt
BrowserAutomator/test/__init__.py
BrowserAutomator/test/mocks.py
BrowserAutomator/test/test_cipher_util.py
BrowserAutomator/test/test_file_reader.py
BrowserAutomator/test/test_loop_actions.py
BrowserAutomator/test/test_network.py
BrowserAutomator/test/test_runner.py
BrowserAutomator/test/test_selenium_setup.py
BrowserAutomator/test/test_setup.py
BrowserAutomator/test/test_setup_actions.py