Metadata-Version: 2.1
Name: BrowserAutomator
Version: 1.0.9
Summary: A package to simplify browser automation
Home-page: https://github.com/edekadigital/BrowserAutomator
Author: EDEKA DIGITAL
License: UNKNOWN
Platform: UNKNOWN
Classifier: Programming Language :: Python :: 3
Classifier: License :: OSI Approved :: MIT License
Classifier: Operating System :: OS Independent
Requires-Python: >=3.3
